wrtrade/__init__.py
wrtrade/__main__.py
wrtrade/brokers.py
wrtrade/brokers_options.py
wrtrade/brokers_real.py
wrtrade/charts.py
wrtrade/cli.py
wrtrade/components.py
wrtrade/data_handler.py
wrtrade/deploy.py
wrtrade/deployment.py
wrtrade/kelly.py
wrtrade/local_deploy.py
wrtrade/metrics.py
wrtrade/ndimensional_portfolio.py
wrtrade/permutation.py
wrtrade/portfolio.py
wrtrade/strategy.py
wrtrade/trade.py
wrtrade-2.1.0.dist-info/licenses/LICENSE
wrtrade-2.1.0.dist-info/METADATA
wrtrade-2.1.0.dist-info/WHEEL
wrtrade-2.1.0.dist-info/entry_points.txt
wrtrade-2.1.0.dist-info/top_level.txt
wrtrade-2.1.0.dist-info/RECORD
