Metadata-Version: 2.4
Name: wrtrade
Version: 2.1.0
Summary: Ultra-fast backtesting and trading framework. Built with Polars for speed, designed for simplicity.
Home-page: https://github.com/wayy-research/wrtrade
Author: Wayy Research
Author-email: contact@wayy.research
Project-URL: Bug Reports, https://github.com/wayy-research/wrtrade/issues
Project-URL: Documentation, https://wrtrade.readthedocs.io/
Project-URL: Source, https://github.com/wayy-research/wrtrade
Keywords: trading,portfolio,quantitative,finance,algorithmic,kelly,optimization,backtesting,deployment,brokers
Classifier: Development Status :: 4 - Beta
Classifier: Intended Audience :: Financial and Insurance Industry
Classifier: Intended Audience :: Developers
Classifier: License :: OSI Approved :: MIT License
Classifier: Operating System :: OS Independent
Classifier: Programming Language :: Python :: 3
Classifier: Programming Language :: Python :: 3.8
Classifier: Programming Language :: Python :: 3.9
Classifier: Programming Language :: Python :: 3.10
Classifier: Programming Language :: Python :: 3.11
Classifier: Topic :: Office/Business :: Financial :: Investment
Classifier: Topic :: Scientific/Engineering :: Mathematics
Classifier: Topic :: Software Development :: Libraries :: Python Modules
Requires-Python: >=3.8
License-File: LICENSE
Requires-Dist: polars>=0.18.0
Requires-Dist: numpy>=1.21.0
Requires-Dist: scipy>=1.7.0
Requires-Dist: click>=8.0.0
Requires-Dist: pyyaml>=6.0.0
Requires-Dist: psutil>=5.8.0
Requires-Dist: aiohttp>=3.8.0
Requires-Dist: requests>=2.28.0
Requires-Dist: pandas>=1.3.0
Requires-Dist: wrchart>=0.1.1
Provides-Extra: alpaca
Requires-Dist: alpaca-trade-api>=3.0.0; extra == "alpaca"
Provides-Extra: robinhood
Requires-Dist: robin-stocks>=2.0.0; extra == "robinhood"
Provides-Extra: all
Requires-Dist: alpaca-trade-api>=3.0.0; extra == "all"
Requires-Dist: robin-stocks>=2.0.0; extra == "all"
Provides-Extra: dev
Requires-Dist: pytest>=7.0.0; extra == "dev"
Requires-Dist: pytest-asyncio>=0.20.0; extra == "dev"
Requires-Dist: black>=22.0.0; extra == "dev"
Requires-Dist: flake8>=4.0.0; extra == "dev"
Requires-Dist: mypy>=0.950; extra == "dev"
Dynamic: author
Dynamic: author-email
Dynamic: classifier
Dynamic: description
Dynamic: description-content-type
Dynamic: home-page
Dynamic: keywords
Dynamic: license-file
Dynamic: project-url
Dynamic: provides-extra
Dynamic: requires-dist
Dynamic: requires-python
Dynamic: summary
